<?xml version = '1.0' encoding = 'UTF-8'?>
<TableProxyOraclev12c class="oracle.dbtools.crest.model.design.storage.oracle.v12c.TableProxyOraclev12c" name="BOOKCOPY" directorySegmentName="seg_0" id="C5272D2F-B057-1030-56AE-EA4C85E3BF39">
<createdBy>macbook</createdBy>
<createdTime>2020-04-21 08:16:52 UTC</createdTime>
<ownerDesignName>relational_model_v2</ownerDesignName>
<schemaObject>4391B17C-795A-5A3F-1185-913CFF3568A6</schemaObject>
<logging>YES</logging>
<partitionedRowMovement>DISABLE</partitionedRowMovement>
<segment>34D14658-99D5-06CF-5CB6-ABF08425C814</segment>
<tableSpace>A07991DC-74EC-6125-ADB5-2987DA44EC8A</tableSpace>
<temporaryChanged>false</temporaryChanged>
<accessDriverType>oracle_loader</accessDriverType>
<rejectLimit></rejectLimit>
<inMemory>NO</inMemory>
<columnProxies itemClass="oracle.dbtools.crest.model.design.storage.oracle.v12c.ColumnProxyOraclev12c">
<ColumnProxy name="ISBN" id="A9F8E24D-B767-A29E-E18E-5A22F64CB97F">
<createdBy>macbook</createdBy>
<createdTime>2020-04-21 08:16:52 UTC</createdTime>
<ownerDesignName>relational_model_v2</ownerDesignName>
</ColumnProxy>
<ColumnProxy name="BARCODE" id="E0CD0E63-1EE8-461D-5B00-D1339BF14F61">
<createdBy>macbook</createdBy>
<createdTime>2020-04-21 08:16:52 UTC</createdTime>
<ownerDesignName>relational_model_v2</ownerDesignName>
</ColumnProxy>
<ColumnProxy name="AVAILABLE" id="E82B9969-EB23-F9AA-64AD-CFAC6D7AF135">
<createdBy>macbook</createdBy>
<createdTime>2020-04-21 08:16:52 UTC</createdTime>
<ownerDesignName>relational_model_v2</ownerDesignName>
</ColumnProxy>
</columnProxies>
<indexProxies>
<IndexProxy class="oracle.dbtools.crest.model.design.storage.oracle.v10g.IndexProxyOraclev10g" name="PK_BOOKCOPY" id="63A3DFC7-1910-3157-A43C-4AF482DAD4E7">
<createdBy>macbook</createdBy>
<createdTime>2020-04-21 08:16:53 UTC</createdTime>
<ownerDesignName>relational_model_v2</ownerDesignName>
<schemaObject>4391B17C-795A-5A3F-1185-913CFF3568A6</schemaObject>
<segment>CBBBE3CC-1996-1DDF-E067-FA274FBF84D1</segment>
<tableSpace>A07991DC-74EC-6125-ADB5-2987DA44EC8A</tableSpace>
</IndexProxy>
</indexProxies>
<foreignKeys>
<ForeignKey class="oracle.dbtools.crest.model.design.storage.oracle.v10g.FKProxyOraclev10g" name="FK_BOOKCOPY" id="23DA2157-D15D-8F10-0844-23830A7B63BD">
<createdBy>macbook</createdBy>
<createdTime>2020-04-21 08:16:55 UTC</createdTime>
<ownerDesignName>relational_model_v2</ownerDesignName>
</ForeignKey>
</foreignKeys>
<primaryKeys>
<PrimaryKey class="oracle.dbtools.crest.model.design.storage.oracle.v10g.PKProxyOraclev10g" name="PK_BOOKCOPY" id="8D3E947D-4FBD-038B-E0AF-C5BA3FC9BDC4">
<createdBy>macbook</createdBy>
<createdTime>2020-04-21 08:16:54 UTC</createdTime>
<ownerDesignName>relational_model_v2</ownerDesignName>
<segment>CBBBE3CC-1996-1DDF-E067-FA274FBF84D1</segment>
<tableSpace>A07991DC-74EC-6125-ADB5-2987DA44EC8A</tableSpace>
<existingIndex>63A3DFC7-1910-3157-A43C-4AF482DAD4E7</existingIndex>
<indexSegment>CBBBE3CC-1996-1DDF-E067-FA274FBF84D1</indexSegment>
<indexSort>SORTED</indexSort>
<usingIndex>BY INDEX NAME</usingIndex>
</PrimaryKey>
</primaryKeys>
</TableProxyOraclev12c>
